setup.py
anhengtimuflag/__init__.py
anhengtimuflag/flag.py
anhengtimuflag.egg-info/PKG-INFO
anhengtimuflag.egg-info/SOURCES.txt
anhengtimuflag.egg-info/dependency_links.txt
anhengtimuflag.egg-info/top_level.txt